sinaraml_jupyter/__init__.py
sinaraml_jupyter/_version.py
sinaraml_jupyter/org_manager.py
sinaraml_jupyter/sinaraml_jupyter.py
sinaraml_jupyter-2024.9.24.1.dist-info/METADATA
sinaraml_jupyter-2024.9.24.1.dist-info/WHEEL
sinaraml_jupyter-2024.9.24.1.dist-info/entry_points.txt
sinaraml_jupyter-2024.9.24.1.dist-info/licenses/LICENSE
sinaraml_jupyter-2024.9.24.1.dist-info/RECORD
