Metadata-Version: 2.3
Name: sinaraml_jupyter
Version: 2024.9.24.1
Summary: SinaraML Jupyter CLI
Project-URL: Homepage, https://github.com/4-DS/sinaraml_jupyter
Author-email: sinaraml <sinaraml.official@gmail.com>
License-File: LICENSE
Keywords: cli,jupyter,sinaraml
Classifier: Operating System :: OS Independent
Classifier: Programming Language :: Python :: 3.6
Classifier: Programming Language :: Python :: 3.7
Classifier: Programming Language :: Python :: 3.8
Classifier: Programming Language :: Python :: Implementation :: CPython
Classifier: Topic :: Scientific/Engineering :: Artificial Intelligence
Requires-Python: >=3.6
Requires-Dist: importlib-metadata; python_version >= '3.6'
